LICENSE
dailies/config/__init__.py
dailies/config/constants.py
dailies/config/dialogue_en.py
dailies/config/paths.py
dailies/config/wordle_words.txt
dailies/file_interaction/__init__.py
dailies/file_interaction/read.py
dailies/games/__init__.py
dailies/games/connections/__init__.py
dailies/games/connections/connections.py
dailies/games/game_infrastructure.py
dailies/games/kenken/__init__.py
dailies/games/kenken/kenken.py
dailies/games/mini_crossword/__init__.py
dailies/games/mini_crossword/mini_crossword.py
dailies/games/strands/__init__.py
dailies/games/strands/strands.py
dailies/games/sudoku/__init__.py
dailies/games/sudoku/sudoku.py
dailies/games/wordle/__init__.py
dailies/games/wordle/wordle.py
dailies/interface/__init__.py
dailies/interface/graphical_menu.py
dailies/logs/__init__.py
dailies/logs/setup_logging.py
dailies/main.py
dailies/py.typed
dailies/VERSION
dailies-0.1.2.dist-info/entry_points.txt
dailies-0.1.2.dist-info/LICENSE
dailies-0.1.2.dist-info/METADATA
dailies-0.1.2.dist-info/WHEEL
dailies-0.1.2.dist-info/RECORD
