Metadata-Version: 2.1
Name: dailies
Version: 0.1.2
Summary: A collection of daily games inspired by NYT Games.
Home-page: https://github.com/unkokaeru/dailies
License: MIT
Author: W. Fayers
Author-email: wills@fayers.com
Requires-Python: >=3.8,<4.0
Classifier: License :: OSI Approved :: MIT License
Classifier: Programming Language :: Python :: 3
Classifier: Programming Language :: Python :: 3.8
Classifier: Programming Language :: Python :: 3.9
Classifier: Programming Language :: Python :: 3.10
Classifier: Programming Language :: Python :: 3.11
Classifier: Programming Language :: Python :: 3.12
Provides-Extra: dev
Provides-Extra: devlint
Provides-Extra: docs
Provides-Extra: lint
Provides-Extra: release
Provides-Extra: test
Provides-Extra: types
Requires-Dist: rich (>=12.0.0,<13.0.0)
Project-URL: Repository, https://github.com/unkokaeru/dailies
